scope/__init__.py
scope/cli.py
scope/aws/__init__.py
scope/aws/collector.py
scope/aws/parser.py
scope/aws/timeline.py
scope/common/__init__.py
scope/common/timeline.py
scope/common/utils.py
scope_forensics-1.0.0.dist-info/licenses/LICENSE
scope_forensics-1.0.0.dist-info/METADATA
scope_forensics-1.0.0.dist-info/WHEEL
scope_forensics-1.0.0.dist-info/entry_points.txt
scope_forensics-1.0.0.dist-info/top_level.txt
scope_forensics-1.0.0.dist-info/RECORD
