Metadata-Version: 2.4
Name: scope-forensics
Version: 1.0.0
Summary: Scope is an Open Source Cloud Forensics tool for AWS. Scope can rapidly obtain logs, discover resources, and create super timelines for analysis.
Author-email: Scope <scopeforensics@protonmail.com>
Project-URL: Homepage, https://github.com/scope-forensics/scope
Project-URL: Bug Tracker, https://github.com/scope-forensics/scope/issues
Classifier: Programming Language :: Python :: 3
Classifier: Operating System :: OS Independent
Requires-Python: >=3.6
License-File: LICENSE
Requires-Dist: boto3>=1.24.0
Requires-Dist: botocore>=1.27.0
Dynamic: license-file
